certbot_dns_buddy/__init__.py
certbot_dns_buddy/dns_buddy.py
certbot_dns_buddy/dns_buddy_test.py
certbot_dns_buddy-1.1.0.dist-info/licenses/LICENSE
certbot_dns_buddy-1.1.0.dist-info/METADATA
certbot_dns_buddy-1.1.0.dist-info/WHEEL
certbot_dns_buddy-1.1.0.dist-info/entry_points.txt
certbot_dns_buddy-1.1.0.dist-info/top_level.txt
certbot_dns_buddy-1.1.0.dist-info/RECORD
